html_tstring/__init__.py
html_tstring/classnames.py
html_tstring/nodes.py
html_tstring/parser.py
html_tstring/processor.py
html_tstring/utils.py
html_tstring-0.1.2.dist-info/METADATA
html_tstring-0.1.2.dist-info/WHEEL
html_tstring-0.1.2.dist-info/licenses/LICENSE
html_tstring-0.1.2.dist-info/RECORD
