Metadata-Version: 2.4
Name: html-tstring
Version: 0.1.2
Summary: A 🤘 rockin' t-string HTML templating system for Python 3.14.
Project-URL: Homepage, https://github.com/t-strings/html-tstring
Project-URL: Changelog, https://github.com/t-strings/html-tstring/releases
Project-URL: Issues, https://github.com/t-strings/html-tstring/issues
Project-URL: CI, https://github.com/t-strings/html-tstring/actions
Author-email: Dave Peck <davepeck@davepeck.org>
License: MIT
License-File: LICENSE
Classifier: Development Status :: 2 - Pre-Alpha
Classifier: Environment :: Web Environment
Classifier: Intended Audience :: Developers
Classifier: License :: OSI Approved :: MIT License
Classifier: Operating System :: OS Independent
Classifier: Programming Language :: Python :: 3 :: Only
Classifier: Programming Language :: Python :: 3.14
Classifier: Topic :: Internet :: WWW/HTTP :: Dynamic Content
Classifier: Topic :: Text Processing :: Markup :: HTML
Classifier: Typing :: Typed
Requires-Python: >=3.14
Requires-Dist: markupsafe>=3.0.2
